{"schedulePeriod":{"ordinal":1,"low":{"ordinal":1,"season":2009,"startEpochMilli":"1252404000000"},"value":1},"eligibleSchedulePeriods":[{"ordinal":1,"low":{"ordinal":1,"season":2009,"startEpochMilli":"1252404000000"},"value":1},{"ordinal":2,"low":{"ordinal":2,"season":2009,"startEpochMilli":"1253008800000"},"value":2},{"ordinal":3,"low":{"ordinal":3,"season":2009,"startEpochMilli":"1253613600000"},"value":3},{"ordinal":4,"low":{"ordinal":4,"season":2009,"startEpochMilli":"1254218400000"},"value":4},{"ordinal":5,"low":{"ordinal":5,"season":2009,"startEpochMilli":"1254823200000"},"value":5},{"ordinal":6,"low":{"ordinal":6,"season":2009,"startEpochMilli":"1255428000000"},"value":6},{"ordinal":7,"low":{"ordinal":7,"season":2009,"startEpochMilli":"1256032800000"},"value":7},{"ordinal":8,"low":{"ordinal":8,"season":2009,"startEpochMilli":"1256637600000"},"value":8},{"ordinal":9,"low":{"ordinal":9,"season":2009,"startEpochMilli":"1257246000000"},"value":9},{"ordinal":10,"low":{"ordinal":10,"season":2009,"startEpochMilli":"1257850800000"},"value":10},{"ordinal":11,"low":{"ordinal":11,"season":2009,"startEpochMilli":"1258455600000"},"value":11},{"ordinal":12,"low":{"ordinal":12,"season":2009,"startEpochMilli":"1259060400000"},"value":12},{"ordinal":13,"low":{"ordinal":13,"season":2009,"startEpochMilli":"1259665200000"},"value":13},{"ordinal":14,"low":{"ordinal":14,"season":2009,"startEpochMilli":"1260270000000"},"value":14},{"ordinal":15,"low":{"ordinal":15,"season":2009,"startEpochMilli":"1260874800000"},"value":15},{"ordinal":16,"low":{"ordinal":16,"season":2009,"startEpochMilli":"1261479600000"},"value":16}],"games":[{"id":"8445152","away":{"id":253597,"name":"Shimshon Shkins","recordOverall":{"wins":4,"losses":10,"winPercentage":{"value":0.2857143,"formatted":".286"},"rank":11,"formatted":"4-10"},"recordDivision":{"wins":3,"losses":7,"winPercentage":{"value":0.3,"formatted":".300"},"rank":5,"formatted":"3-7"},"recordPostseason":{"wins":1,"losses":1,"winPercentage":{"value":0.5,"formatted":".500"},"rank":11,"formatted":"1-1"},"pointsFor":{"value":1197.0,"formatted":"1,197"},"pointsAgainst":{"value":1306.0,"formatted":"1,306"},"streak":{"value":-1.0,"formatted":"L1"},"waiverPosition":4,"initials":"SS"},"home":{"id":253601,"name":"Single Malts","logoUrl":"https://s3.amazonaws.com/fleaflicker/t253601_0_150x150.jpg","recordOverall":{"wins":7,"losses":7,"winPercentage":{"value":0.5,"formatted":".500"},"rank":2,"formatted":"7-7"},"recordDivision":{"wins":5,"losses":5,"winPercentage":{"value":0.5,"formatted":".500"},"rank":2,"formatted":"5-5"},"recordPostseason":{"wins":1,"losses":1,"winPercentage":{"value":0.5,"formatted":".500"},"rank":4,"formatted":"1-1"},"pointsFor":{"value":1206.0,"formatted":"1,206"},"pointsAgainst":{"value":1166.0,"formatted":"1,166"},"streak":{"value":1.0,"formatted":"W1"},"waiverPosition":9,"initials":"SM"},"awayScore":{"score":{"value":77.0,"formatted":"77"}},"homeScore":{"score":{"value":97.0,"formatted":"97"}},"homeResult":"WIN","awayResult":"LOSE","isFinalScore":true,"isDivisional":true},{"id":"8445151","away":{"id":253598,"name":"Vandelay Industries","recordOverall":{"wins":6,"losses":8,"winPercentage":{"value":0.42857143,"formatted":".429"},"rank":9,"formatted":"6-8"},"recordDivision":{"wins":5,"losses":5,"winPercentage":{"value":0.5,"formatted":".500"},"rank":3,"formatted":"5-5"},"recordPostseason":{"wins":2,"winPercentage":{"value":1.0,"formatted":"1.000"},"rank":9,"formatted":"2-0"},"pointsFor":{"value":1173.0,"formatted":"1,173"},"pointsAgainst":{"value":1195.0,"formatted":"1,195"},"streak":{"value":-2.0,"formatted":"L2"},"waiverPosition":10,"newItemCounts":{"activityUnread":254,"messagesUnread":243},"initials":"VI"},"home":{"id":253600,"name":"RBS Penguins","recordOverall":{"wins":2,"losses":12,"winPercentage":{"value":0.14285715,"formatted":".143"},"rank":12,"formatted":"2-12"},"recordDivision":{"wins":2,"losses":8,"winPercentage":{"value":0.2,"formatted":".200"},"rank":6,"formatted":"2-8"},"recordPostseason":{"wins":1,"losses":1,"winPercentage":{"value":0.5,"formatted":".500"},"rank":12,"formatted":"1-1"},"pointsFor":{"value":956.0,"formatted":"956"},"pointsAgainst":{"value":1307.0,"formatted":"1,307"},"streak":{"value":-1.0,"formatted":"L1"},"waiverPosition":5,"initials":"RP"},"awayScore":{"score":{"value":64.0,"formatted":"64"}},"homeScore":{"score":{"value":68.0,"formatted":"68"}},"homeResult":"WIN","awayResult":"LOSE","isFinalScore":true,"isDivisional":true},{"id":"8445155","away":{"id":253599,"name":"Baltimore Splinter Cells","logoUrl":"https://s3.amazonaws.com/fleaflicker/t253599_0_150x150.jpg","recordOverall":{"wins":8,"losses":6,"winPercentage":{"value":0.5714286,"formatted":".571"},"rank":5,"formatted":"8-6"},"recordDivision":{"wins":4,"losses":6,"winPercentage":{"value":0.4,"formatted":".400"},"rank":5,"formatted":"4-6"},"recordPostseason":{"wins":1,"losses":1,"winPercentage":{"value":0.5,"formatted":".500"},"rank":7,"formatted":"1-1"},"pointsFor":{"value":1268.0,"formatted":"1,268"},"pointsAgainst":{"value":1194.0,"formatted":"1,194"},"streak":{"value":-1.0,"formatted":"L1"},"waiverPosition":1,"newItemCounts":{"activityUnread":255,"messagesUnread":255},"initials":"BS"},"home":{"id":253605,"name":"QPR Giants","recordOverall":{"wins":6,"losses":8,"winPercentage":{"value":0.42857143,"formatted":".429"},"rank":8,"formatted":"6-8"},"recordDivision":{"wins":5,"losses":5,"winPercentage":{"value":0.5,"formatted":".500"},"rank":6,"formatted":"5-5"},"recordPostseason":{"wins":1,"losses":1,"winPercentage":{"value":0.5,"formatted":".500"},"rank":8,"formatted":"1-1"},"pointsFor":{"value":1274.0,"formatted":"1,274"},"pointsAgainst":{"value":1358.0,"formatted":"1,358"},"streak":{"value":1.0,"formatted":"W1"},"waiverPosition":6,"newItemCounts":{"activityUnread":38,"messagesUnread":255},"initials":"QG"},"awayScore":{"score":{"value":113.0,"formatted":"113"}},"homeScore":{"score":{"value":83.0,"formatted":"83"}},"homeResult":"LOSE","awayResult":"WIN","isFinalScore":true,"isDivisional":true},{"id":"8445153","away":{"id":253602,"name":"Olmert Audibles","logoUrl":"https://s3.amazonaws.com/fleaflicker/t253602_0_150x150.jpg","recordOverall":{"wins":6,"losses":8,"winPercentage":{"value":0.42857143,"formatted":".429"},"rank":10,"formatted":"6-8"},"recordDivision":{"wins":6,"losses":4,"winPercentage":{"value":0.6,"formatted":".600"},"rank":4,"formatted":"6-4"},"recordPostseason":{"losses":2,"winPercentage":{"formatted":".000"},"rank":10,"formatted":"0-2"},"pointsFor":{"value":958.0,"formatted":"958"},"pointsAgainst":{"value":1198.0,"formatted":"1,198"},"streak":{"value":1.0,"formatted":"W1"},"waiverPosition":2,"newItemCounts":{"activityUnread":255,"messagesUnread":206},"initials":"OA"},"home":{"id":253608,"name":"What Time Zone is This?","logoUrl":"https://s3.amazonaws.com/fleaflicker/t253608_0_150x150.jpg","recordOverall":{"wins":12,"losses":2,"winPercentage":{"value":0.85714287,"formatted":".857"},"rank":3,"formatted":"12-2"},"recordDivision":{"wins":9,"losses":1,"winPercentage":{"value":0.9,"formatted":".900"},"rank":1,"formatted":"9-1"},"recordPostseason":{"wins":1,"losses":1,"winPercentage":{"value":0.5,"formatted":".500"},"rank":1,"formatted":"1-1"},"pointsFor":{"value":1544.0,"formatted":"1,544"},"pointsAgainst":{"value":1168.0,"formatted":"1,168"},"streak":{"value":8.0,"formatted":"W8"},"waiverPosition":7,"newItemCounts":{"activityUnread":255,"messagesUnread":255},"initials":"WT"},"awayScore":{"score":{"value":33.0,"formatted":"33"}},"homeScore":{"score":{"value":106.0,"formatted":"106"}},"homeResult":"WIN","awayResult":"LOSE","isFinalScore":true,"isDivisional":true},{"id":"8445154","away":{"id":253603,"name":"Raven Maniacs","recordOverall":{"wins":8,"losses":6,"winPercentage":{"value":0.5714286,"formatted":".571"},"rank":6,"formatted":"8-6"},"recordDivision":{"wins":5,"losses":5,"winPercentage":{"value":0.5,"formatted":".500"},"rank":2,"formatted":"5-5"},"recordPostseason":{"losses":2,"winPercentage":{"formatted":".000"},"rank":3,"formatted":"0-2"},"pointsFor":{"value":1243.0,"formatted":"1,243"},"pointsAgainst":{"value":1110.0,"formatted":"1,110"},"streak":{"value":-2.0,"formatted":"L2"},"waiverPosition":8,"newItemCounts":{"activityUnread":115,"messagesUnread":255},"initials":"RM"},"home":{"id":253604,"name":"Eli Manning is not Jewish","recordOverall":{"wins":9,"losses":5,"winPercentage":{"value":0.64285713,"formatted":".643"},"rank":1,"formatted":"9-5"},"recordDivision":{"wins":7,"losses":3,"winPercentage":{"value":0.7,"formatted":".700"},"rank":1,"formatted":"7-3"},"recordPostseason":{"wins":2,"winPercentage":{"value":1.0,"formatted":"1.000"},"rank":2,"formatted":"2-0"},"pointsFor":{"value":1166.0,"formatted":"1,166"},"pointsAgainst":{"value":1127.0,"formatted":"1,127"},"streak":{"value":3.0,"formatted":"W3"},"waiverPosition":11,"newItemCounts":{"messagesUnread":2},"initials":"EM"},"awayScore":{"score":{"value":63.0,"formatted":"63"}},"homeScore":{"score":{"value":82.0,"formatted":"82"}},"homeResult":"WIN","awayResult":"LOSE","isFinalScore":true,"isDivisional":true},{"id":"8445156","away":{"id":253606,"name":"Super Spurs","logoUrl":"https://s3.amazonaws.com/fleaflicker/t253606_0_150x150.jpg","recordOverall":{"wins":8,"losses":6,"winPercentage":{"value":0.5714286,"formatted":".571"},"rank":7,"formatted":"8-6"},"recordDivision":{"wins":5,"losses":5,"winPercentage":{"value":0.5,"formatted":".500"},"rank":3,"formatted":"5-5"},"recordPostseason":{"wins":2,"winPercentage":{"value":1.0,"formatted":"1.000"},"rank":5,"formatted":"2-0"},"pointsFor":{"value":1142.0,"formatted":"1,142"},"pointsAgainst":{"value":1110.0,"formatted":"1,110"},"streak":{"value":2.0,"formatted":"W2"},"waiverPosition":12,"newItemCounts":{"activityUnread":255,"messagesUnread":255},"initials":"SS"},"home":{"id":253607,"name":"RBS Storm","logoUrl":"https://s3.amazonaws.com/fleaflicker/t253607_0_150x150.jpg","recordOverall":{"wins":8,"losses":6,"winPercentage":{"value":0.5714286,"formatted":".571"},"rank":4,"formatted":"8-6"},"recordDivision":{"wins":4,"losses":6,"winPercentage":{"value":0.4,"formatted":".400"},"rank":4,"formatted":"4-6"},"recordPostseason":{"losses":2,"winPercentage":{"formatted":".000"},"rank":6,"formatted":"0-2"},"pointsFor":{"value":1344.0,"formatted":"1,344"},"pointsAgainst":{"value":1232.0,"formatted":"1,232"},"streak":{"value":-3.0,"formatted":"L3"},"waiverPosition":3,"initials":"RS"},"awayScore":{"score":{"value":102.0,"formatted":"102"}},"homeScore":{"score":{"value":100.0,"formatted":"100"}},"homeResult":"LOSE","awayResult":"WIN","isFinalScore":true,"isDivisional":true}]}
