{
    "year": "2025",
    "week": 17,
    "games": [
        {
            "team1": {
                "teamnum": "3",
                "players": [
                    {
                        "name": "Drake Maye",
                        "key": "461.p.40881",
                        "position": "QB",
                        "primary_position": "QB",
                        "points": "32.44"
                    },
                    {
                        "name": "Nico Collins",
                        "key": "461.p.33477",
                        "position": "WR",
                        "primary_position": "WR",
                        "points": "8.70"
                    },
                    {
                        "name": "Jaxon Smith-Njigba",
                        "key": "461.p.40041",
                        "position": "WR",
                        "primary_position": "WR",
                        "points": "16.20"
                    },
                    {
                        "name": "RJ Harvey",
                        "key": "461.p.41845",
                        "position": "RB",
                        "primary_position": "RB",
                        "points": "18.60"
                    },
                    {
                        "name": "Kenneth Walker III",
                        "key": "461.p.33996",
                        "position": "RB",
                        "primary_position": "RB",
                        "points": "7.70"
                    },
                    {
                        "name": "Trey McBride",
                        "key": "461.p.34010",
                        "position": "TE",
                        "primary_position": "TE",
                        "points": "23.60"
                    },
                    {
                        "name": "Javonte Williams",
                        "key": "461.p.33423",
                        "position": "W/R/T",
                        "primary_position": "RB",
                        "points": "11.40"
                    },
                    {
                        "name": "Christian Watson",
                        "key": "461.p.33989",
                        "position": "BN",
                        "primary_position": "WR",
                        "points": "22.30"
                    },
                    {
                        "name": "Brian Thomas Jr.",
                        "key": "461.p.40883",
                        "position": "BN",
                        "primary_position": "WR",
                        "points": "7.90"
                    },
                    {
                        "name": "TreVeyon Henderson",
                        "key": "461.p.41823",
                        "position": "BN",
                        "primary_position": "RB",
                        "points": "8.20"
                    },
                    {
                        "name": "Jordan Love",
                        "key": "461.p.32696",
                        "position": "BN",
                        "primary_position": "QB",
                        "points": "0.00"
                    },
                    {
                        "name": "J.J. McCarthy",
                        "key": "461.p.40905",
                        "position": "BN",
                        "primary_position": "QB",
                        "points": "0.00"
                    },
                    {
                        "name": "Romeo Doubs",
                        "key": "461.p.34088",
                        "position": "BN",
                        "primary_position": "WR",
                        "points": "9.20"
                    },
                    {
                        "name": "Brandon McManus",
                        "key": "461.p.27120",
                        "position": "K",
                        "primary_position": "K",
                        "points": "6.00"
                    },
                    {
                        "name": "Chargers",
                        "key": "461.p.100024",
                        "position": "DEF",
                        "primary_position": "DEF",
                        "points": "5.00"
                    }
                ],
                "points": "129.64",
                "projected": "135.26"
            },
            "team2": {
                "teamnum": "8",
                "players": [
                    {
                        "name": "DJ Moore",
                        "key": "461.p.30994",
                        "position": "BN",
                        "primary_position": "WR",
                        "points": "1.70"
                    },
                    {
                        "name": "Omarion Hampton",
                        "key": "461.p.41807",
                        "position": "BN",
                        "primary_position": "RB",
                        "points": "20.00"
                    },
                    {
                        "name": "James Cook III",
                        "key": "461.p.34019",
                        "position": "BN",
                        "primary_position": "RB",
                        "points": "8.70"
                    },
                    {
                        "name": "Ja'Marr Chase",
                        "key": "461.p.33393",
                        "position": "BN",
                        "primary_position": "WR",
                        "points": "25.00"
                    },
                    {
                        "name": "Zay Flowers",
                        "key": "461.p.40039",
                        "position": "BN",
                        "primary_position": "WR",
                        "points": "13.00"
                    },
                    {
                        "name": "Theo Johnson",
                        "key": "461.p.41003",
                        "position": "BN",
                        "primary_position": "TE",
                        "points": "0.00"
                    },
                    {
                        "name": "Darnell Mooney",
                        "key": "461.p.32843",
                        "position": "BN",
                        "primary_position": "WR",
                        "points": "5.50"
                    },
                    {
                        "name": "Zach Charbonnet",
                        "key": "461.p.40075",
                        "position": "BN",
                        "primary_position": "RB",
                        "points": "26.20"
                    },
                    {
                        "name": "Emanuel Wilson",
                        "key": "461.p.40707",
                        "position": "BN",
                        "primary_position": "RB",
                        "points": "3.40"
                    }
                ],
                "points": "0.00",
                "projected": "0.00"
            }
        },
        {
            "team1": {
                "teamnum": "4",
                "players": [
                    {
                        "name": "Tyler Shough",
                        "key": "461.p.41825",
                        "position": "QB",
                        "primary_position": "QB",
                        "points": "21.92"
                    },
                    {
                        "name": "Davante Adams",
                        "key": "461.p.27581",
                        "position": "WR",
                        "primary_position": "WR",
                        "points": "0.00"
                    },
                    {
                        "name": "Stefon Diggs",
                        "key": "461.p.28534",
                        "position": "WR",
                        "primary_position": "WR",
                        "points": "22.10"
                    },
                    {
                        "name": "Derrick Henry",
                        "key": "461.p.29279",
                        "position": "RB",
                        "primary_position": "RB",
                        "points": "45.60"
                    },
                    {
                        "name": "Ashton Jeanty",
                        "key": "461.p.41791",
                        "position": "RB",
                        "primary_position": "RB",
                        "points": "9.30"
                    },
                    {
                        "name": "Brenton Strange",
                        "key": "461.p.40078",
                        "position": "TE",
                        "primary_position": "TE",
                        "points": "8.40"
                    },
                    {
                        "name": "Kyle Monangai",
                        "key": "461.p.42025",
                        "position": "W/R/T",
                        "primary_position": "RB",
                        "points": "7.70"
                    },
                    {
                        "name": "Aaron Jones Sr.",
                        "key": "461.p.30295",
                        "position": "BN",
                        "primary_position": "RB",
                        "points": "15.30"
                    },
                    {
                        "name": "Devin Neal",
                        "key": "461.p.41972",
                        "position": "BN",
                        "primary_position": "RB",
                        "points": "0.00"
                    },
                    {
                        "name": "Tez Johnson",
                        "key": "461.p.42030",
                        "position": "BN",
                        "primary_position": "WR",
                        "points": "3.90"
                    },
                    {
                        "name": "Oronde Gadsden",
                        "key": "461.p.41951",
                        "position": "BN",
                        "primary_position": "TE",
                        "points": "12.20"
                    },
                    {
                        "name": "Cam Ward",
                        "key": "461.p.41786",
                        "position": "BN",
                        "primary_position": "QB",
                        "points": "18.04"
                    },
                    {
                        "name": "Luther Burden III",
                        "key": "461.p.41824",
                        "position": "BN",
                        "primary_position": "WR",
                        "points": "27.80"
                    },
                    {
                        "name": "Eddy Pineiro",
                        "key": "461.p.31482",
                        "position": "K",
                        "primary_position": "K",
                        "points": "6.00"
                    },
                    {
                        "name": "Giants",
                        "key": "461.p.100019",
                        "position": "DEF",
                        "primary_position": "DEF",
                        "points": "18.00"
                    },
                    {
                        "name": "Jayden Daniels",
                        "key": "461.p.40896",
                        "position": "IR",
                        "primary_position": "QB",
                        "points": "0.00"
                    }
                ],
                "points": "139.02",
                "projected": "102.23"
            },
            "team2": {
                "teamnum": "11",
                "players": [
                    {
                        "name": "Josh Allen",
                        "key": "461.p.30977",
                        "position": "QB",
                        "primary_position": "QB",
                        "points": "23.18"
                    },
                    {
                        "name": "Tetairoa McMillan",
                        "key": "461.p.41793",
                        "position": "WR",
                        "primary_position": "WR",
                        "points": "1.50"
                    },
                    {
                        "name": "Chris Godwin Jr.",
                        "key": "461.p.30197",
                        "position": "WR",
                        "primary_position": "WR",
                        "points": "23.80"
                    },
                    {
                        "name": "Bijan Robinson",
                        "key": "461.p.40055",
                        "position": "RB",
                        "primary_position": "RB",
                        "points": "40.90"
                    },
                    {
                        "name": "Bucky Irving",
                        "key": "461.p.40993",
                        "position": "RB",
                        "primary_position": "RB",
                        "points": "8.30"
                    },
                    {
                        "name": "George Kittle",
                        "key": "461.p.30259",
                        "position": "TE",
                        "primary_position": "TE",
                        "points": "0.00"
                    },
                    {
                        "name": "Jauan Jennings",
                        "key": "461.p.32887",
                        "position": "W/R/T",
                        "primary_position": "WR",
                        "points": "12.20"
                    },
                    {
                        "name": "Khalil Shakir",
                        "key": "461.p.34104",
                        "position": "BN",
                        "primary_position": "WR",
                        "points": "9.50"
                    },
                    {
                        "name": "Juwan Johnson",
                        "key": "461.p.33113",
                        "position": "BN",
                        "primary_position": "TE",
                        "points": "13.50"
                    },
                    {
                        "name": "Xavier Worthy",
                        "key": "461.p.40877",
                        "position": "BN",
                        "primary_position": "WR",
                        "points": "0.10"
                    },
                    {
                        "name": "Tre Tucker",
                        "key": "461.p.40114",
                        "position": "BN",
                        "primary_position": "WR",
                        "points": "9.90"
                    },
                    {
                        "name": "Nick Chubb",
                        "key": "461.p.31005",
                        "position": "BN",
                        "primary_position": "RB",
                        "points": "0.10"
                    },
                    {
                        "name": "Jaxson Dart",
                        "key": "461.p.41810",
                        "position": "BN",
                        "primary_position": "QB",
                        "points": "25.08"
                    },
                    {
                        "name": "Wil Lutz",
                        "key": "461.p.29754",
                        "position": "K",
                        "primary_position": "K",
                        "points": "8.00"
                    },
                    {
                        "name": "49ers",
                        "key": "461.p.100025",
                        "position": "DEF",
                        "primary_position": "DEF",
                        "points": "-3.00"
                    },
                    {
                        "name": "J.K. Dobbins",
                        "key": "461.p.32725",
                        "position": "IR",
                        "primary_position": "RB",
                        "points": "0.00"
                    }
                ],
                "points": "114.88",
                "projected": "112.27"
            }
        },
        {
            "team1": {
                "teamnum": "6",
                "players": [
                    {
                        "name": "Matthew Stafford",
                        "key": "461.p.9265",
                        "position": "QB",
                        "primary_position": "QB",
                        "points": "12.76"
                    },
                    {
                        "name": "Amon-Ra St. Brown",
                        "key": "461.p.33500",
                        "position": "WR",
                        "primary_position": "WR",
                        "points": "14.80"
                    },
                    {
                        "name": "Michael Wilson",
                        "key": "461.p.40121",
                        "position": "WR",
                        "primary_position": "WR",
                        "points": "19.90"
                    },
                    {
                        "name": "D'Andre Swift",
                        "key": "461.p.32705",
                        "position": "RB",
                        "primary_position": "RB",
                        "points": "21.90"
                    },
                    {
                        "name": "Jonathan Taylor",
                        "key": "461.p.32711",
                        "position": "RB",
                        "primary_position": "RB",
                        "points": "17.40"
                    },
                    {
                        "name": "Tyler Warren",
                        "key": "461.p.41799",
                        "position": "TE",
                        "primary_position": "TE",
                        "points": "9.30"
                    },
                    {
                        "name": "Chris Olave",
                        "key": "461.p.33966",
                        "position": "W/R/T",
                        "primary_position": "WR",
                        "points": "25.90"
                    },
                    {
                        "name": "Kenneth Gainwell",
                        "key": "461.p.33538",
                        "position": "BN",
                        "primary_position": "RB",
                        "points": "6.80"
                    },
                    {
                        "name": "Darius Slayton",
                        "key": "461.p.32003",
                        "position": "BN",
                        "primary_position": "WR",
                        "points": "5.60"
                    },
                    {
                        "name": "Elic Ayomanor",
                        "key": "461.p.41904",
                        "position": "BN",
                        "primary_position": "WR",
                        "points": "13.70"
                    },
                    {
                        "name": "Aaron Rodgers",
                        "key": "461.p.7200",
                        "position": "BN",
                        "primary_position": "QB",
                        "points": "7.32"
                    },
                    {
                        "name": "Dalton Schultz",
                        "key": "461.p.31107",
                        "position": "BN",
                        "primary_position": "TE",
                        "points": "4.90"
                    },
                    {
                        "name": "Hunter Henry",
                        "key": "461.p.29269",
                        "position": "BN",
                        "primary_position": "TE",
                        "points": "13.90"
                    },
                    {
                        "name": "Brandon Aubrey",
                        "key": "461.p.40819",
                        "position": "K",
                        "primary_position": "K",
                        "points": "17.00"
                    },
                    {
                        "name": "Lions",
                        "key": "461.p.100008",
                        "position": "DEF",
                        "primary_position": "DEF",
                        "points": "11.00"
                    },
                    {
                        "name": "Cam Skattebo",
                        "key": "461.p.41922",
                        "position": "IR",
                        "primary_position": "RB",
                        "points": "0.00"
                    }
                ],
                "points": "149.96",
                "projected": "136.85"
            },
            "team2": {
                "teamnum": "7",
                "players": [
                    {
                        "name": "Bo Nix",
                        "key": "461.p.40875",
                        "position": "QB",
                        "primary_position": "QB",
                        "points": "19.48"
                    },
                    {
                        "name": "Puka Nacua",
                        "key": "461.p.40168",
                        "position": "WR",
                        "primary_position": "WR",
                        "points": "15.70"
                    },
                    {
                        "name": "Ladd McConkey",
                        "key": "461.p.40908",
                        "position": "WR",
                        "primary_position": "WR",
                        "points": "4.10"
                    },
                    {
                        "name": "Tyrone Tracy Jr.",
                        "key": "461.p.41048",
                        "position": "RB",
                        "primary_position": "RB",
                        "points": "6.70"
                    },
                    {
                        "name": "Christian McCaffrey",
                        "key": "461.p.30121",
                        "position": "RB",
                        "primary_position": "RB",
                        "points": "28.10"
                    },
                    {
                        "name": "Jake Ferguson",
                        "key": "461.p.34085",
                        "position": "TE",
                        "primary_position": "TE",
                        "points": "7.60"
                    },
                    {
                        "name": "Michael Carter",
                        "key": "461.p.33495",
                        "position": "W/R/T",
                        "primary_position": "RB",
                        "points": "6.30"
                    },
                    {
                        "name": "Rashee Rice",
                        "key": "461.p.40084",
                        "position": "BN",
                        "primary_position": "WR",
                        "points": "0.00"
                    },
                    {
                        "name": "DK Metcalf",
                        "key": "461.p.31896",
                        "position": "BN",
                        "primary_position": "WR",
                        "points": "0.00"
                    },
                    {
                        "name": "Kareem Hunt",
                        "key": "461.p.30199",
                        "position": "BN",
                        "primary_position": "RB",
                        "points": "3.80"
                    },
                    {
                        "name": "Quentin Johnston",
                        "key": "461.p.40051",
                        "position": "BN",
                        "primary_position": "WR",
                        "points": "14.80"
                    },
                    {
                        "name": "Alvin Kamara",
                        "key": "461.p.30180",
                        "position": "BN",
                        "primary_position": "RB",
                        "points": "0.00"
                    },
                    {
                        "name": "Blake Corum",
                        "key": "461.p.40962",
                        "position": "BN",
                        "primary_position": "RB",
                        "points": "1.80"
                    },
                    {
                        "name": "Ka'imi Fairbairn",
                        "key": "461.p.29792",
                        "position": "K",
                        "primary_position": "K",
                        "points": "10.00"
                    },
                    {
                        "name": "Saints",
                        "key": "461.p.100018",
                        "position": "DEF",
                        "primary_position": "DEF",
                        "points": "12.00"
                    },
                    {
                        "name": "Patrick Mahomes",
                        "key": "461.p.30123",
                        "position": "IR",
                        "primary_position": "QB",
                        "points": "0.00"
                    }
                ],
                "points": "109.98",
                "projected": "128.36"
            }
        },
        {
            "team1": {
                "teamnum": "9",
                "players": [
                    {
                        "name": "Dak Prescott",
                        "key": "461.p.29369",
                        "position": "QB",
                        "primary_position": "QB",
                        "points": "23.68"
                    },
                    {
                        "name": "Michael Pittman Jr.",
                        "key": "461.p.32704",
                        "position": "WR",
                        "primary_position": "WR",
                        "points": "3.60"
                    },
                    {
                        "name": "Jaylen Waddle",
                        "key": "461.p.33394",
                        "position": "WR",
                        "primary_position": "WR",
                        "points": "0.70"
                    },
                    {
                        "name": "Jahmyr Gibbs",
                        "key": "461.p.40059",
                        "position": "RB",
                        "primary_position": "RB",
                        "points": "6.40"
                    },
                    {
                        "name": "De'Von Achane",
                        "key": "461.p.40118",
                        "position": "RB",
                        "primary_position": "RB",
                        "points": "14.20"
                    },
                    {
                        "name": "Mark Andrews",
                        "key": "461.p.31056",
                        "position": "TE",
                        "primary_position": "TE",
                        "points": "6.80"
                    },
                    {
                        "name": "Tony Pollard",
                        "key": "461.p.31960",
                        "position": "W/R/T",
                        "primary_position": "RB",
                        "points": "11.50"
                    },
                    {
                        "name": "Wan'Dale Robinson",
                        "key": "461.p.33998",
                        "position": "BN",
                        "primary_position": "WR",
                        "points": "22.30"
                    },
                    {
                        "name": "Parker Washington",
                        "key": "461.p.40234",
                        "position": "BN",
                        "primary_position": "WR",
                        "points": "19.00"
                    },
                    {
                        "name": "Rhamondre Stevenson",
                        "key": "461.p.33508",
                        "position": "BN",
                        "primary_position": "RB",
                        "points": "27.20"
                    },
                    {
                        "name": "Brock Purdy",
                        "key": "461.p.34218",
                        "position": "BN",
                        "primary_position": "QB",
                        "points": "36.92"
                    },
                    {
                        "name": "Kayshon Boutte",
                        "key": "461.p.40224",
                        "position": "BN",
                        "primary_position": "WR",
                        "points": "0.00"
                    },
                    {
                        "name": "Cameron Dicker",
                        "key": "461.p.34344",
                        "position": "K",
                        "primary_position": "K",
                        "points": "2.00"
                    },
                    {
                        "name": "Titans",
                        "key": "461.p.100010",
                        "position": "DEF",
                        "primary_position": "DEF",
                        "points": "1.00"
                    },
                    {
                        "name": "Patriots",
                        "key": "461.p.100017",
                        "position": "BN",
                        "primary_position": "DEF",
                        "points": "7.00"
                    },
                    {
                        "name": "Mike Evans",
                        "key": "461.p.27535",
                        "position": "IR",
                        "primary_position": "WR",
                        "points": "12.10"
                    }
                ],
                "points": "69.88",
                "projected": "122.46"
            },
            "team2": {
                "teamnum": "12",
                "players": [
                    {
                        "name": "Baker Mayfield",
                        "key": "461.p.30971",
                        "position": "QB",
                        "primary_position": "QB",
                        "points": "17.44"
                    },
                    {
                        "name": "Courtland Sutton",
                        "key": "461.p.31010",
                        "position": "WR",
                        "primary_position": "WR",
                        "points": "8.00"
                    },
                    {
                        "name": "Terry McLaurin",
                        "key": "461.p.31908",
                        "position": "WR",
                        "primary_position": "WR",
                        "points": "11.30"
                    },
                    {
                        "name": "Kyren Williams",
                        "key": "461.p.34120",
                        "position": "RB",
                        "primary_position": "RB",
                        "points": "16.00"
                    },
                    {
                        "name": "Saquon Barkley",
                        "key": "461.p.30972",
                        "position": "RB",
                        "primary_position": "RB",
                        "points": "6.80"
                    },
                    {
                        "name": "Travis Kelce",
                        "key": "461.p.26686",
                        "position": "TE",
                        "primary_position": "TE",
                        "points": "8.60"
                    },
                    {
                        "name": "Rashid Shaheed",
                        "key": "461.p.34659",
                        "position": "W/R/T",
                        "primary_position": "WR",
                        "points": "1.80"
                    },
                    {
                        "name": "Cooper Kupp",
                        "key": "461.p.30182",
                        "position": "BN",
                        "primary_position": "WR",
                        "points": "1.60"
                    },
                    {
                        "name": "Jacory Croskey-Merritt",
                        "key": "461.p.42010",
                        "position": "BN",
                        "primary_position": "RB",
                        "points": "23.50"
                    },
                    {
                        "name": "Devaughn Vele",
                        "key": "461.p.41097",
                        "position": "BN",
                        "primary_position": "WR",
                        "points": "0.00"
                    },
                    {
                        "name": "Jared Goff",
                        "key": "461.p.29235",
                        "position": "BN",
                        "primary_position": "QB",
                        "points": "2.08"
                    },
                    {
                        "name": "Ricky Pearsall",
                        "key": "461.p.40892",
                        "position": "BN",
                        "primary_position": "WR",
                        "points": "13.50"
                    },
                    {
                        "name": "Cedric Tillman",
                        "key": "461.p.40093",
                        "position": "BN",
                        "primary_position": "WR",
                        "points": "5.20"
                    },
                    {
                        "name": "Cam Little",
                        "key": "461.p.41062",
                        "position": "K",
                        "primary_position": "K",
                        "points": "14.00"
                    },
                    {
                        "name": "Broncos",
                        "key": "461.p.100007",
                        "position": "DEF",
                        "primary_position": "DEF",
                        "points": "9.00"
                    }
                ],
                "points": "92.94",
                "projected": "114.24"
            }
        }
    ]
}